txfrestframeworkjwt/__init__.py
txfrestframeworkjwt/authentication.py
txfrestframeworkjwt/compat.py
txfrestframeworkjwt/models.py
txfrestframeworkjwt/serializers.py
txfrestframeworkjwt/settings.py
txfrestframeworkjwt/test.py
txfrestframeworkjwt/utils.py
txfrestframeworkjwt/views.py
txfrestframeworkjwt-4.1.dist-info/METADATA
txfrestframeworkjwt-4.1.dist-info/WHEEL
txfrestframeworkjwt-4.1.dist-info/top_level.txt
txfrestframeworkjwt-4.1.dist-info/zip-safe
txfrestframeworkjwt-4.1.dist-info/RECORD
