Metadata-Version: 2.1
Name: txfrestframeworkjwt
Version: 4.1
Summary: jwt
Author: wu-di-tian-ge-ge
Author-email: 402066270@qq.com
License: NEU
Classifier: Programming Language :: Python
Classifier: Intended Audience :: Developers
Classifier: Operating System :: OS Independent
Requires-Dist: django
Requires-Dist: djangorestframework
